smart_pipeline/__init__.py
smart_pipeline/pipeline.py
smart_pipeline-1.0.0.dist-info/LICENSE
smart_pipeline-1.0.0.dist-info/METADATA
smart_pipeline-1.0.0.dist-info/WHEEL
smart_pipeline-1.0.0.dist-info/top_level.txt
smart_pipeline-1.0.0.dist-info/RECORD
